semanticclean
