Metadata-Version: 2.1
Name: semanticclean
Version: 0.11
Summary: A simple package to find label issues
Home-page: UNKNOWN
Author: elshehawy@iSemantics
Author-email: a.elshehawy64@gmail.com
License: UNKNOWN
Platform: UNKNOWN
